MANIFEST.in
README.md
setup.py
name_karwowski.egg-info/PKG-INFO
name_karwowski.egg-info/SOURCES.txt
name_karwowski.egg-info/dependency_links.txt
name_karwowski.egg-info/top_level.txt
nameskarwowski/__init__.py
nameskarwowski/nameskarwowski.py