Metadata-Version: 1.0
Name: name-karwowski
Version: 1.0.0
Summary: funny
Home-page: UNKNOWN
Author: Paweł_Karwowski
Author-email: pawel-karwowski@o2.pl
License: UNKNOWN
Platform: UNKNOWN
